{
  "schemaVersion": 1,
  "id": "extraons",
  "version": "${version}",

  "name": "Extra-Ons",
  "description": "An Add-on mod that was originally made for MrCrayfish's Device Mod back in 2018 and is now back as a fabric port in 2021!!!",
  "authors": [
    "spjoes"
  ],
  "contact": {
    "sources": "https://github.com/spjoes/Extra-ons/tree/Extra-Ons-2-2021"
  },

  "license": "CC0-1.0",
  "icon": "assets/extraons/icon.png",

  "environment": "*",
  "entrypoints": {
    "main": [
      "com.split.extraons.Main"
    ],
    "client": [
      "com.split.extraons.MainClient"
    ],
    "rei_plugins": [
      "com.split.extraons.REIPlugin"
    ]
  },
  "mixins": [
    "extraons.mixins.json"
  ],

  "depends": {
    "fabricloader": ">=0.7.4",
    "fabric": "*",
    "minecraft": "1.16.x"
  },
  "suggests": {
    "another-mod": "*"
  },
  "accessWidener": "extraons.accesswidener"
}
